open_fortran_parser/OpenFortranParser-0.8.5-1.jar
open_fortran_parser/OpenFortranParserXML-0.6.1.jar
open_fortran_parser/__init__.py
open_fortran_parser/__main__.py
open_fortran_parser/_version.py
open_fortran_parser/antlr-3.5.2-complete.jar
open_fortran_parser/commons-cli-1.4.jar
open_fortran_parser/config.py
open_fortran_parser/dependencies.py
open_fortran_parser/main.py
open_fortran_parser/ofc_wrapper.py
open_fortran_parser/org.jacoco.agent-0.8.3-runtime.jar
open_fortran_parser/org.jacoco.cli-0.8.3-nodeps.jar
open_fortran_parser/parser_wrapper.py
open_fortran_parser/py.typed
open_fortran_parser-0.6.1.dist-info/LICENSE
open_fortran_parser-0.6.1.dist-info/METADATA
open_fortran_parser-0.6.1.dist-info/NOTICE
open_fortran_parser-0.6.1.dist-info/WHEEL
open_fortran_parser-0.6.1.dist-info/top_level.txt
open_fortran_parser-0.6.1.dist-info/RECORD
